metgrs/CloudRadar.py
metgrs/Lidar.py
metgrs/MicroWaveRadiometer.py
metgrs/Utils.py
metgrs/WindProfileRadar.py
metgrs/__init__.py
metgrs/__version__.py
metgrs/base.py
metgrs-0.4.9.dist-info/LICENSE
metgrs-0.4.9.dist-info/METADATA
metgrs-0.4.9.dist-info/WHEEL
metgrs-0.4.9.dist-info/top_level.txt
metgrs-0.4.9.dist-info/RECORD
