Metadata-Version: 2.2
Name: metgrs
Version: 0.4.9
Summary: The Python Package work for The Ground-based Remote Sensing Data Operation.
Home-page: https://github.com/longtsing/metgrs/
Author: Longtsing
Author-email: longtsing <longtsing@cug.edu.cn>
License:                     GNU GENERAL PUBLIC LICENSE
Project-URL: homepage, https://github.com/longtsing/metgrs
Project-URL: issues, https://github.com/longtsing/metgrs/issues
Classifier: Programming Language :: Python :: 3
Classifier: License :: OSI Approved :: GNU General Public License v3 (GPLv3)
Classifier: Operating System :: OS Independent
Requires-Python: >=3.8.0
License-File: LICENSE
Requires-Dist: matplotlib>=3.1
Requires-Dist: numpy>=1.21.5
Requires-Dist: pandas>=1.0.4
Requires-Dist: xarray>=0.10.0
Requires-Dist: joblib>=1.0
Requires-Dist: python-dateutil>=1.0
Dynamic: author
Dynamic: home-page
Dynamic: requires-python
